MANIFEST.in
README.rst
setup.py
Products/__init__.py
Products.PloneSoftwareCenter.egg-info/PKG-INFO
Products.PloneSoftwareCenter.egg-info/SOURCES.txt
Products.PloneSoftwareCenter.egg-info/dependency_links.txt
Products.PloneSoftwareCenter.egg-info/entry_points.txt
Products.PloneSoftwareCenter.egg-info/namespace_packages.txt
Products.PloneSoftwareCenter.egg-info/not-zip-safe
Products.PloneSoftwareCenter.egg-info/requires.txt
Products.PloneSoftwareCenter.egg-info/top_level.txt
Products/PloneSoftwareCenter/TROVE.txt
Products/PloneSoftwareCenter/__init__.py
Products/PloneSoftwareCenter/config.py
Products/PloneSoftwareCenter/configure.zcml
Products/PloneSoftwareCenter/interfaces.py
Products/PloneSoftwareCenter/permissions.py
Products/PloneSoftwareCenter/profiles.zcml
Products/PloneSoftwareCenter/pypi.py
Products/PloneSoftwareCenter/refresh.txt
Products/PloneSoftwareCenter/setuphandlers.py
Products/PloneSoftwareCenter/tests.py
Products/PloneSoftwareCenter/trove.py
Products/PloneSoftwareCenter/utils.py
Products/PloneSoftwareCenter/validators.py
Products/PloneSoftwareCenter/Extensions/.cvsignore
Products/PloneSoftwareCenter/Extensions/AreaWorkflow.py
Products/PloneSoftwareCenter/Extensions/ImprovementProposalWorkflow.py
Products/PloneSoftwareCenter/Extensions/Install.py
Products/PloneSoftwareCenter/Extensions/Migrations.py
Products/PloneSoftwareCenter/Extensions/PackageWorkflow.py
Products/PloneSoftwareCenter/Extensions/ReleaseWorkflow.py
Products/PloneSoftwareCenter/Extensions/WorkflowScripts.py
Products/PloneSoftwareCenter/Extensions/__init__.py
Products/PloneSoftwareCenter/Extensions/migrateratings.py
Products/PloneSoftwareCenter/browser/__init__.py
Products/PloneSoftwareCenter/browser/category.py
Products/PloneSoftwareCenter/browser/configure.zcml
Products/PloneSoftwareCenter/browser/docfolder.py
Products/PloneSoftwareCenter/browser/downloadablefile.py
Products/PloneSoftwareCenter/browser/fancyzoom.js
Products/PloneSoftwareCenter/browser/filelink.py
Products/PloneSoftwareCenter/browser/improvement.py
Products/PloneSoftwareCenter/browser/project.py
Products/PloneSoftwareCenter/browser/projectdoap.py
Products/PloneSoftwareCenter/browser/pypi.py
Products/PloneSoftwareCenter/browser/pypilinks.pt
Products/PloneSoftwareCenter/browser/pypilinks.py
Products/PloneSoftwareCenter/browser/release.py
Products/PloneSoftwareCenter/browser/releasefolder.py
Products/PloneSoftwareCenter/browser/roadmap.py
