Metadata-Version: 1.0
Name: Products.PloneSoftwareCenter
Version: 1.6.4
Summary: PloneSoftwareCenter is a tool that keeps track of software projects
